diff_tracer/__init__.py
diff_tracer/diff_match_patch.py
diff_tracer/fastapi_example.py
diff_tracer/main.py
diff_tracer/utils.py
diff_tracer/view.html
diff_tracer/view.py
diff_tracer-0.0.1.dist-info/LICENSE
diff_tracer-0.0.1.dist-info/METADATA
diff_tracer-0.0.1.dist-info/WHEEL
diff_tracer-0.0.1.dist-info/RECORD
