Metadata-Version: 2.1
Name: diff_tracer
Version: 0.0.1
Summary: 
Author: Beto Figueiredo
Requires-Python: >=3.12.2,<4.0.0
Classifier: Programming Language :: Python :: 3
Requires-Dist: fastapi (>=0.115.5,<0.116.0)
Requires-Dist: fastapi-cli (>=0.0.5,<0.0.6)
Requires-Dist: gunicorn (>=23.0.0,<24.0.0)
Requires-Dist: jinja2 (>=3.1.4,<4.0.0)
Requires-Dist: pydantic (>=2.6.4,<3.0.0)
Requires-Dist: uvicorn[standard] (>=0.32.1,<0.33.0)
